timewheel/__init__.py
timewheel/schedule.py
timewheel/wheel.py
timewheel_scheduler-0.3.0.dist-info/METADATA
timewheel_scheduler-0.3.0.dist-info/WHEEL
timewheel_scheduler-0.3.0.dist-info/top_level.txt
timewheel_scheduler-0.3.0.dist-info/RECORD
