Metadata-Version: 2.1
Name: timewheel-scheduler
Version: 0.3.0
Summary: Async crontab like scheduler
Author: Fausto Alonso
Author-email: falonso@gmail.com
License: MIT
